[{"name":"Kelly Mosciski","desc":"transition schemas"},{"name":"Marc Kuphal","desc":"syndicate collaborative web services"},{"name":"Regan Hessel.","desc":"collaborative web services"},{"name":"Saul Emmerich","desc":"syndicate web services"},{"name":"Francisca Rempel","desc":"facilitate holistic synergies"},{"name":"Asa Cartwright","desc":"leverage frictionless channels"},{"name":"Miss Enrico Dickinson","desc":"reinvent transparent initiatives"},{"name":"Asa Cartwright","desc":"integrate transparent mindshare"},{"name":"Murl King","desc":"leverage frictionless channels"},{"name":"Murl King","desc":"frictionless channels"}]